README.md
setup.cfg
setup.py
outliers/__init__.py
outliers/outliers.py
outliers_ashikothari10.egg-info/PKG-INFO
outliers_ashikothari10.egg-info/SOURCES.txt
outliers_ashikothari10.egg-info/dependency_links.txt
outliers_ashikothari10.egg-info/top_level.txt